my_package/__init__.py
my_package/odd_checker.py
my_package/text_utils.py
utkarsh_odd_vowels-0.1.0.dist-info/licenses/LICENCE
utkarsh_odd_vowels-0.1.0.dist-info/METADATA
utkarsh_odd_vowels-0.1.0.dist-info/WHEEL
utkarsh_odd_vowels-0.1.0.dist-info/top_level.txt
utkarsh_odd_vowels-0.1.0.dist-info/RECORD
